easymcserver/__init__.py
easymcserver/cli.py
easymcserver/download.py
easymcserver/utils.py
easymcserver-0.1.3.dist-info/licenses/LICENSE
easymcserver-0.1.3.dist-info/METADATA
easymcserver-0.1.3.dist-info/WHEEL
easymcserver-0.1.3.dist-info/entry_points.txt
easymcserver-0.1.3.dist-info/top_level.txt
easymcserver-0.1.3.dist-info/RECORD
