Metadata-Version: 2.4
Name: easymcserver
Version: 0.1.3
Summary: CLI para facilitar a instalação de servidores Java e Bedrock
Requires-Python: >=3.10
License-File: LICENSE
Requires-Dist: requests
Requires-Dist: rich
Requires-Dist: InquirerPy
Requires-Dist: psutil
Dynamic: license-file
